LICENSE
README.md
setup.py
src/wordz/__init__.py
src/wordz/base.py
src/wordz/cli.py
src/wordz/logs.py
src/wordz/version.py
src/wordz.egg-info/PKG-INFO
src/wordz.egg-info/SOURCES.txt
src/wordz.egg-info/dependency_links.txt
src/wordz.egg-info/entry_points.txt
src/wordz.egg-info/not-zip-safe
src/wordz.egg-info/top_level.txt