Metadata-Version: 2.1
Name: wordz
Version: 0.1.7
Summary: Wordlists builder
Home-page: https://github.com/tasooshi/wordz
Author: tasooshi
Author-email: tasooshi@pm.me
License: BSD License
Keywords: wordlists,bruteforce,dictionary,generator,hashcat
Classifier: Development Status :: 4 - Beta
Classifier: Topic :: Utilities
Classifier: License :: OSI Approved :: BSD License
Classifier: Programming Language :: Python :: 3.9
Classifier: Programming Language :: Python :: 3.10
Requires-Python: >=3.9
License-File: LICENSE
